LICENSE
README.md
setup.py
axa_safeai/__init__.py
axa_safeai/check_explainability.py
axa_safeai/check_fairness.py
axa_safeai/check_robustness.py
axa_safeai/core.py
axa_safeai.egg-info/PKG-INFO
axa_safeai.egg-info/SOURCES.txt
axa_safeai.egg-info/dependency_links.txt
axa_safeai.egg-info/top_level.txt
axa_safeai/util/__init__.py
axa_safeai/util/utils.py
tests/__init__.py
tests/test_functions.py