Metadata-Version: 2.1
Name: axa_safeai
Version: 0.2.2
Summary: AXA SAFE AI package to measure accuracy, explainability, fairness and robustness of any classification and regression model.
Author: Golnoosh Babaei
Author-email: <golnoosh.babaei@unipv.it>
Classifier: Development Status :: 1 - Planning
Classifier: Intended Audience :: Developers
Classifier: Programming Language :: Python :: 3
Classifier: Operating System :: Unix
Classifier: Operating System :: MacOS :: MacOS X
Classifier: Operating System :: Microsoft :: Windows
License-File: LICENSE
